raspend/__init__.py
raspend/application.py
raspend/http.py
raspend/utils/__init__.py
raspend/utils/commandmapping.py
raspend/utils/serviceshutdownhandling.py
raspend/utils/stoppablehttpserver.py
raspend/utils/workerthreads.py
raspend-2.0.4.dist-info/LICENSE
raspend-2.0.4.dist-info/METADATA
raspend-2.0.4.dist-info/WHEEL
raspend-2.0.4.dist-info/top_level.txt
raspend-2.0.4.dist-info/RECORD
