Metadata-Version: 2.1
Name: raspend
Version: 2.0.4
Summary: A lightweight web service framework.
Home-page: https://github.com/jobe3774/raspend.git
Author: Joerg Beckers
Author-email: pypi@jobe-software.de
License: MIT
Platform: UNKNOWN
Classifier: Programming Language :: Python :: 3
Classifier: License :: OSI Approved :: MIT License
Classifier: Operating System :: OS Independent
Classifier: Topic :: Home Automation
Requires-Python: >=3.5
